micado/__init__.py
micado/cli.py
micado/client.py
micado/exceptions.py
micado/settings.py
micado/api/__init__.py
micado/api/application.py
micado/api/client.py
micado/installer/__init__.py
micado/installer/ansible/__init__.py
micado/installer/ansible/ansible.py
micado/installer/ansible/playbook.py
micado/launcher/__init__.py
micado/launcher/cloudbroker/__init__.py
micado/launcher/cloudbroker/cloudbroker.py
micado/launcher/openstack/__init__.py
micado/launcher/openstack/auth.py
micado/launcher/openstack/openstack.py
micado/models/__init__.py
micado/models/application.py
micado/models/base.py
micado/models/micado.py
micado/types/__init__.py
micado/types/applications.py
micado/types/micado.py
micado/utils/__init__.py
micado/utils/utils.py
micado_client-0.12.13.dist-info/LICENSE
micado_client-0.12.13.dist-info/METADATA
micado_client-0.12.13.dist-info/WHEEL
micado_client-0.12.13.dist-info/entry_points.txt
micado_client-0.12.13.dist-info/top_level.txt
micado_client-0.12.13.dist-info/RECORD
